fasttokenizer/__init__.py
fasttokenizer/_fasttokenizer.cpython-37m-darwin.so
fasttokenizer-0.0.2.dist-info/LICENSE
fasttokenizer-0.0.2.dist-info/METADATA
fasttokenizer-0.0.2.dist-info/WHEEL
fasttokenizer-0.0.2.dist-info/top_level.txt
fasttokenizer-0.0.2.dist-info/RECORD
